marketing_measures/__init__.py
marketing_measures/marketing_emphasis_scorer.py
marketing_measures/data/marketing_capabilities_presentation_zca.npz
marketing_measures/data/marketing_excellence_presentation_zca.npz
marketing_measures/data/marketing_orientation_presentation_zca.npz
marketing_measures/seeds/marketing_capabilities.json
marketing_measures/seeds/marketing_excellence.json
marketing_measures/seeds/marketing_orientation.json
marketing_measures-0.1.5.dist-info/licenses/LICENSE
marketing_measures-0.1.5.dist-info/METADATA
marketing_measures-0.1.5.dist-info/WHEEL
marketing_measures-0.1.5.dist-info/top_level.txt
marketing_measures-0.1.5.dist-info/RECORD
