Metadata-Version: 2.4
Name: marketing-measures
Version: 0.1.5
Summary: A Python package for measuring marketing emphasis in text data using Hugging Face transformers and multiple marketing constructs.
Home-page: https://github.com/yourusername/marketing_measures
Author: Your Name
Author-email: "Hoorsana Damavandi, Feng Mai, Vivek Astvansh" <hdamavan@utk.edu>
Project-URL: Homepage, https://github.com/Marketing-Measures/marketing-measures
Project-URL: Bug Tracker, https://github.com/Marketing-Measures/marketing-measures/issues
Project-URL: Documentation, https://github.com/Marketing-Measures/marketing-measures#readme
Classifier: Development Status :: 4 - Beta
Classifier: Intended Audience :: Science/Research
Classifier: Topic :: Text Processing :: Linguistic
Classifier: Topic :: Scientific/Engineering :: Artificial Intelligence
Classifier: Programming Language :: Python :: 3
Classifier: Programming Language :: Python :: 3.8
Classifier: Programming Language :: Python :: 3.9
Classifier: Programming Language :: Python :: 3.10
Classifier: Programming Language :: Python :: 3.11
Classifier: License :: OSI Approved :: MIT License
Classifier: Operating System :: OS Independent
Requires-Python: >=3.8
License-File: LICENSE
Requires-Dist: numpy>=1.0.0
Requires-Dist: pandas>=1.0.0
Requires-Dist: scipy>=1.2.0
Requires-Dist: scikit-learn>=1.0.0
Requires-Dist: transformers>=3.0.0
Requires-Dist: torch>=0.8.0
Provides-Extra: dev
Requires-Dist: pytest>=6.0; extra == "dev"
Requires-Dist: pytest-cov>=2.0; extra == "dev"
Requires-Dist: black>=22.0; extra == "dev"
Requires-Dist: flake8>=4.0; extra == "dev"
Requires-Dist: mypy>=0.900; extra == "dev"
Dynamic: author
Dynamic: home-page
Dynamic: license-file
Dynamic: requires-python
